AUTHORS.rst
CONTRIBUTING.rst
HISTORY.md
LICENSE
MANIFEST.in
README.md
pyproject.toml
requirements.txt
setup.cfg
setup.py
altamisa/__init__.py
altamisa/exceptions.py
altamisa/py.typed
altamisa/version.py
altamisa.egg-info/PKG-INFO
altamisa.egg-info/SOURCES.txt
altamisa.egg-info/dependency_links.txt
altamisa.egg-info/entry_points.txt
altamisa.egg-info/not-zip-safe
altamisa.egg-info/requires.txt
altamisa.egg-info/top_level.txt
altamisa/apps/__init__.py
altamisa/apps/isatab2dot.py
altamisa/apps/isatab2isatab.py
altamisa/apps/isatab_validate.py
altamisa/constants/__init__.py
altamisa/constants/investigation_headers.py
altamisa/constants/table_headers.py
altamisa/constants/table_restrictions.py
altamisa/constants/table_tokens.py
altamisa/isatab/__init__.py
altamisa/isatab/headers.py
altamisa/isatab/helpers.py
altamisa/isatab/models.py
altamisa/isatab/parse_assay_study.py
altamisa/isatab/parse_investigation.py
altamisa/isatab/validate_assay_study.py
altamisa/isatab/validate_investigation.py
altamisa/isatab/write_assay_study.py
altamisa/isatab/write_investigation.py
docs/Makefile
docs/api_constants.rst
docs/api_exceptions.rst
docs/api_headers.rst
docs/api_models.rst
docs/api_parsers.rst
docs/api_validators.rst
docs/api_writers.rst
docs/authors.rst
docs/conf.py
docs/contributing.rst
docs/examples.rst
docs/getting_started.rst
docs/history.rst
docs/index.rst
docs/installation.rst
docs/license.rst
docs/make.bat
docs/images/Peruvian_Ragweed-small.png
docs/images/Peruvian_Ragweed.png
requirements/base.txt
requirements/develop.txt
requirements/test.txt
requirements/test_black.txt
tests/__init__.py
tests/conftest.py
tests/test_apps.py
tests/test_exceptions.py
tests/test_model_creation.py
tests/test_parse_assay.py
tests/test_parse_investigation.py
tests/test_parse_study.py
tests/test_write_assay.py
tests/test_write_investigation.py
tests/test_write_study.py
tests/__snapshots__/test_apps.ambr
tests/__snapshots__/test_parse_study.ambr
tests/data/BII-I-1/a_metabolome.txt
tests/data/BII-I-1/a_microarray.txt
tests/data/BII-I-1/a_proteome.txt
tests/data/BII-I-1/a_transcriptome.txt
tests/data/BII-I-1/i_investigation.txt
tests/data/BII-I-1/s_BII-S-1.txt
tests/data/BII-I-1/s_BII-S-2.txt
