Metadata-Version: 2.4
Name: altamisa
Version: 0.3.1
Summary: Implementation of ISA-tools data model and ISA-TAB
Home-page: https://github.com/bihealth/altamisa
Author: Dieter Beule, Jennifer Kirwan, Mathias Kuhring, Manuel Holtgrewe, Mikko Nieminen
Author-email: dieter.beule@bih-charite.de, jennifer.kirwan@bihalth.de, mathias.kuhring@bih-charite.de, manuel.holtgrewe@bih-charite.de, mikko.nieminen@bih-charite.de
License: MIT license
Keywords: altamisa
Classifier: Development Status :: 4 - Beta
Classifier: Intended Audience :: Developers
Classifier: License :: OSI Approved :: MIT License
Classifier: Natural Language :: English
Classifier: Topic :: Scientific/Engineering :: Bio-Informatics
Classifier: Programming Language :: Python :: 3
Classifier: Programming Language :: Python :: 3.10
Classifier: Programming Language :: Python :: 3.11
Classifier: Programming Language :: Python :: 3.12
Classifier: Programming Language :: Python :: 3.13
Classifier: Programming Language :: Python :: 3.14
License-File: LICENSE
License-File: AUTHORS.rst
Requires-Dist: attrs
Requires-Dist: typer[all]
Dynamic: author
Dynamic: author-email
Dynamic: classifier
Dynamic: description
Dynamic: description-content-type
Dynamic: home-page
Dynamic: keywords
Dynamic: license
Dynamic: license-file
Dynamic: requires-dist
Dynamic: summary
